botier/__init__.py
botier/auxiliary_objective.py
botier/hierarchy_scalarization_objective.py
botier/hierarchy_scalarizer.py
botier/utils.py
botier-1.0.0.dist-info/METADATA
botier-1.0.0.dist-info/WHEEL
botier-1.0.0.dist-info/top_level.txt
botier-1.0.0.dist-info/RECORD
