Metadata-Version: 2.2
Name: botier
Version: 1.0.0
Summary: BoTier: Multi-Objective Bayesian Optimization with Tiered Composite Objectives
Author-email: Mohammad Haddadnia <mohammad_haddadnia@dfci.harvard.edu>, Felix Strieth-Kalthoff <strieth-kalthoff@uni-wuppertal.de>, Leonie Grashoff <grashoff@uni-wuppertal.de>
Maintainer-email: Felix Strieth-Kalthoff <strieth-kalthoff@uni-wuppertal.de>, Mohammad Haddadnia <mohammad_haddadnia@dfci.harvard.edu>
License: MIT License
Project-URL: Homepage, https://botier.readthedocs.io
Project-URL: Repository, https://www.github.com/fsk-lab/botier
Project-URL: Bug Tracker, https://github.com/fsk-lab/botier/issues
Classifier: License :: OSI Approved :: MIT License
Classifier: Programming Language :: Python
Classifier: Programming Language :: Python :: 3
Classifier: Programming Language :: Python :: 3 :: Only
Classifier: Programming Language :: Python :: 3.8
Classifier: Programming Language :: Python :: 3.9
Classifier: Programming Language :: Python :: 3.10
Classifier: Programming Language :: Python :: 3.11
Classifier: Programming Language :: Python :: 3.12
Classifier: Intended Audience :: Science/Research
Classifier: Topic :: Software Development
Classifier: Topic :: Scientific/Engineering
Classifier: Topic :: Scientific/Engineering :: Chemistry
Classifier: Topic :: Scientific/Engineering :: Physics
Classifier: Topic :: Scientific/Engineering :: Artificial Intelligence
Requires-Python: >=3.8
Requires-Dist: torch
Requires-Dist: botorch
Requires-Dist: pandas
Provides-Extra: test
Requires-Dist: black; extra == "test"
Requires-Dist: flake8; extra == "test"
Requires-Dist: pytest; extra == "test"
Requires-Dist: pytest-cov; extra == "test"
Requires-Dist: flake8-pyproject; extra == "test"
